betatelsdk/__init__.py
betatelsdk/base.py
betatelsdk/billing.py
betatelsdk/call.py
betatelsdk/carrier.py
betatelsdk/network.py
betatelsdk/sdk.py
betatelsdk/sms.py
betatelsdk/types.py
betatelsdk/validators.py
betatelsdk/voice.py
betatelsdk-0.0.8.dist-info/METADATA
betatelsdk-0.0.8.dist-info/WHEEL
betatelsdk-0.0.8.dist-info/top_level.txt
betatelsdk-0.0.8.dist-info/RECORD
