Metadata-Version: 2.4
Name: betatelsdk
Version: 0.0.8
Summary: An SDK for Betatel services
Author: Betatel LTD
Author-email: <muhamed.b@beta.tel>
Keywords: python,tts,tele,voice,sms,sip,call,betatel
Classifier: Development Status :: 1 - Planning
Classifier: Intended Audience :: Developers
Classifier: Programming Language :: Python :: 3
Classifier: Operating System :: Unix
Classifier: Operating System :: MacOS :: MacOS X
Classifier: Operating System :: Microsoft :: Windows
Requires-Dist: requests
Dynamic: author
Dynamic: author-email
Dynamic: classifier
Dynamic: description
Dynamic: description-content-type
Dynamic: keywords
Dynamic: requires-dist
Dynamic: summary
